st_btn_select/__init__.py
st_btn_select/frontend/build/asset-manifest.json
st_btn_select/frontend/build/bootstrap.min.css
st_btn_select/frontend/build/index.html
st_btn_select/frontend/build/precache-manifest.86a16a32c4e31894afc8b30b90d5c9ed.js
st_btn_select/frontend/build/service-worker.js
st_btn_select/frontend/build/static/css/main.ce6fb195.chunk.css
st_btn_select/frontend/build/static/css/main.ce6fb195.chunk.css.map
st_btn_select/frontend/build/static/js/2.e75ddf8e.chunk.js
st_btn_select/frontend/build/static/js/2.e75ddf8e.chunk.js.LICENSE.txt
st_btn_select/frontend/build/static/js/2.e75ddf8e.chunk.js.map
st_btn_select/frontend/build/static/js/main.48aca1b0.chunk.js
st_btn_select/frontend/build/static/js/main.48aca1b0.chunk.js.map
st_btn_select/frontend/build/static/js/runtime-main.9dc84cf5.js
st_btn_select/frontend/build/static/js/runtime-main.9dc84cf5.js.map
st_btn_select-0.1.2.dist-info/LICENSE
st_btn_select-0.1.2.dist-info/METADATA
st_btn_select-0.1.2.dist-info/WHEEL
st_btn_select-0.1.2.dist-info/top_level.txt
st_btn_select-0.1.2.dist-info/RECORD
