Metadata-Version: 2.1
Name: st-btn-select
Version: 0.1.2
Summary: Streamlit Button Selection Component
Home-page: https://github.com/0phoff/st-btn-select
Author: 0phoff
License: MIT
Platform: UNKNOWN
Requires-Python: >=3.6
